vcc_utils/__init__.py
vcc_utils-100.1.1.dist-info/METADATA
vcc_utils-100.1.1.dist-info/WHEEL
vcc_utils-100.1.1.dist-info/RECORD
